{
  "companyName": "Fidato",

  "companyMainPageLink": "home.html",

  "services": [
    {
      "serviceName": "Consulting",
      "serviceSmallDescription": "Small Description about Service",
      "serviceSmallImage": "../images/consulting_small_5.ico",
      "serviceQuotationBold": "Consulting Services!",
      "serviceQuotationMuted": "Advices are valuable & that's why we are here.",
      "serviceQuotationImage": "../images/consulting_500_1.png",
      "serviceLink": "consulting.html"
    },
    {
      "serviceName": "Technology",
      "serviceSmallDescription": "Small Description about Service",
      "serviceSmallImage": "../images/technology_small_6.png",
      "serviceQuotationBold": "Technology Services!",
      "serviceQuotationMuted": "We beleive in Technology so, let's change the world together.",
      "serviceQuotationImage": "../images/technology_500.png",
      "serviceLink": "technology.html"
    },
    {
      "serviceName": "Recruitment",
      "serviceSmallDescription": "Small Description about Service",
      "serviceSmallImage": "../images/recruitment_small_3.png",
      "serviceQuotationBold": "Recruitment Services!",
      "serviceQuotationMuted": "Human is the best asset for a company & we help you to hire best for you.",
      "serviceQuotationImage": "../images/recruitment_500_1.png",
      "serviceLink": "recruitment.html"
    },
    {
      "serviceName": "Finance",
      "serviceSmallDescription": "Small Description about Service",
      "serviceSmallImage": "../images/finance_small1.png",
      "serviceQuotationBold": "Financial Services!",
      "serviceQuotationMuted": "It is must for every business & we are best at this.",
      "serviceQuotationImage": "../images/finance_500_1.png",
      "serviceLink": "finance.html"
    }
  ],

  "carousalItems": [
    {
      "slideImageSrc": "../images/consulting4.jpg",
      "slideClass": "first-slide",
      "slideImageAltText": "Consulting Service Image",
      "isActive": true
    },
    {
      "slideImageSrc": "../images/training.jpeg",
      "slideClass": "second-slide",
      "slideImageAltText": "Technology Service Image",
      "isActive": false
    },
    {
      "slideImageSrc": "../images/recruitment1.jpg",
      "slideClass": "third-slide",
      "slideImageAltText": "Recruiment Service Image",
      "isActive": false
    },
    {
      "slideImageSrc": "../images/finance2.jpg",
      "slideClass": "fourth-slide",
      "slideImageAltText": "Finance Service Image",
      "isActive": false
    }
  ],

  "menuItems": [
    {
      "name": "Consulting",
      "link": "consulting.html",
      "icon": "user",
      "isActive": false,
      "bannerImage": "../images/consulting_big_1.jpg",
      "headingIcon": "user",
      "headingText": "Consulting Services"
    },
    {
      "name": "Technology",
      "link": "technology.html",
      "icon": "phone",
      "isActive": false,
      "bannerImage": "../images/technology_big_1.jpg",
      "headingIcon": "phone",
      "headingText": "Technology Services"
    },
    {
      "name": "Recruitment",
      "link": "recruitment.html",
      "icon": "globe",
      "isActive": false,
      "bannerImage": "../images/recruitment_big_3.jpg",
      "headingIcon": "globe",
      "headingText": "Recruitment Services"
    },
    {
      "name": "Finance",
      "link": "finance.html",
      "icon": "piggy-bank",
      "isActive": false,
      "bannerImage": "../images/finance_big_2.png",
      "headingIcon": "piggy-bank",
      "headingText": "Financial Services"
    },
    {
      "name": "Contact Us",
      "link": "contact.html",
      "icon": "envelope",
      "isActive": false,
      "bannerImage": "../images/contactus_big_1.jpg",
      "headingIcon": "pencil",
      "headingText": "Write to Us"
    }
  ]
}